{
  "$schema": "https://developer.microsoft.com/json-schemas/fabric/item/report/definition/visualContainer/1.5.0/schema.json",
  "name": "986037e07af62c0a3046",
  "position": {
    "x": 847.857275995207,
    "y": 88.34402875782186,
    "z": 11000,
    "height": 198.77406470509919,
    "width": 177.91505791505793,
    "tabOrder": 10000
  },
  "visual": {
    "visualType": "clusteredBarChart",
    "query": {
      "queryState": {
        "Category": {
          "projections": [
            {
              "field": {
                "Column": {
                  "Expression": {
                    "SourceRef": {
                      "Entity": "Sales Raw Data"
                    }
                  },
                  "Property": "State"
                }
              },
              "queryRef": "Sales Raw Data.State",
              "nativeQueryRef": "State",
              "active": true,
              "displayName": "State"
            }
          ]
        },
        "Y": {
          "projections": [
            {
              "field": {
                "Measure": {
                  "Expression": {
                    "SourceRef": {
                      "Entity": "Calculations"
                    }
                  },
                  "Property": "Total Sales"
                }
              },
              "queryRef": "Calculations.Total Sales",
              "nativeQueryRef": "Total Sales"
            }
          ]
        }
      },
      "sortDefinition": {
        "sort": [
          {
            "field": {
              "Measure": {
                "Expression": {
                  "SourceRef": {
                    "Entity": "Calculations"
                  }
                },
                "Property": "Total Sales"
              }
            },
            "direction": "Descending"
          }
        ],
        "isDefaultSort": true
      }
    },
    "objects": {
      "legend": [
        {
          "properties": {
            "show": {
              "expr": {
                "Literal": {
                  "Value": "false"
                }
              }
            },
            "position": {
              "expr": {
                "Literal": {
                  "Value": "'TopRight'"
                }
              }
            },
            "showTitle": {
              "expr": {
                "Literal": {
                  "Value": "false"
                }
              }
            },
            "labelColor": {
              "solid": {
                "color": {
                  "expr": {
                    "ThemeDataColor": {
                      "ColorId": 0,
                      "Percent": 0
                    }
                  }
                }
              }
            },
            "showGradientLegend": {
              "expr": {
                "Literal": {
                  "Value": "false"
                }
              }
            }
          }
        }
      ],
      "categoryAxis": [
        {
          "properties": {
            "showAxisTitle": {
              "expr": {
                "Literal": {
                  "Value": "false"
                }
              }
            },
            "labelColor": {
              "solid": {
                "color": {
                  "expr": {
                    "Literal": {
                      "Value": "'#505671'"
                    }
                  }
                }
              }
            },
            "innerPadding": {
              "expr": {
                "Literal": {
                  "Value": "13L"
                }
              }
            },
            "concatenateLabels": {
              "expr": {
                "Literal": {
                  "Value": "false"
                }
              }
            },
            "preferredCategoryWidth": {
              "expr": {
                "Literal": {
                  "Value": "20D"
                }
              }
            },
            "maxMarginFactor": {
              "expr": {
                "Literal": {
                  "Value": "37L"
                }
              }
            },
            "fontSize": {
              "expr": {
                "Literal": {
                  "Value": "8D"
                }
              }
            }
          }
        }
      ],
      "valueAxis": [
        {
          "properties": {
            "showAxisTitle": {
              "expr": {
                "Literal": {
                  "Value": "false"
                }
              }
            },
            "labelColor": {
              "solid": {
                "color": {
                  "expr": {
                    "Literal": {
                      "Value": "'#505671'"
                    }
                  }
                }
              }
            },
            "gridlineColor": {
              "solid": {
                "color": {
                  "expr": {
                    "ThemeDataColor": {
                      "ColorId": 0,
                      "Percent": 0
                    }
                  }
                }
              }
            }
          }
        }
      ],
      "dataPoint": [
        {
          "properties": {
            "fill": {
              "solid": {
                "color": {
                  "expr": {
                    "Literal": {
                      "Value": "'#136862'"
                    }
                  }
                }
              }
            }
          },
          "selector": {
            "data": [
              {
                "scopeId": {
                  "Comparison": {
                    "ComparisonKind": 0,
                    "Left": {
                      "Column": {
                        "Expression": {
                          "SourceRef": {
                            "Entity": "Sales Raw Data"
                          }
                        },
                        "Property": "Customer Gender"
                      }
                    },
                    "Right": {
                      "Literal": {
                        "Value": "'M'"
                      }
                    }
                  }
                }
              }
            ]
          }
        },
        {
          "properties": {
            "fill": {
              "solid": {
                "color": {
                  "expr": {
                    "Literal": {
                      "Value": "'#FFE4AD'"
                    }
                  }
                }
              }
            }
          },
          "selector": {
            "data": [
              {
                "scopeId": {
                  "Comparison": {
                    "ComparisonKind": 0,
                    "Left": {
                      "Column": {
                        "Expression": {
                          "SourceRef": {
                            "Entity": "Sales Raw Data"
                          }
                        },
                        "Property": "Customer Gender"
                      }
                    },
                    "Right": {
                      "Literal": {
                        "Value": "'F'"
                      }
                    }
                  }
                }
              }
            ]
          }
        },
        {
          "properties": {
            "fill": {
              "solid": {
                "color": {
                  "expr": {
                    "Literal": {
                      "Value": "'#505671'"
                    }
                  }
                }
              }
            }
          }
        },
        {
          "properties": {
            "fill": {
              "solid": {
                "color": {
                  "expr": {
                    "Literal": {
                      "Value": "'#136862'"
                    }
                  }
                }
              }
            }
          },
          "selector": {
            "metadata": "CountNonNull(Sales Raw Data.Customer Age)"
          }
        },
        {
          "properties": {
            "fill": {
              "solid": {
                "color": {
                  "expr": {
                    "Literal": {
                      "Value": "'#505671'"
                    }
                  }
                }
              }
            }
          },
          "selector": {
            "metadata": "Calculations.Total Sales"
          }
        },
        {
          "properties": {
            "fill": {
              "solid": {
                "color": {
                  "expr": {
                    "Literal": {
                      "Value": "'#505671'"
                    }
                  }
                }
              }
            }
          },
          "selector": {
            "metadata": "Calculations.Total Profit"
          }
        }
      ],
      "layout": [
        {
          "properties": {
            "clusteredGapOverlaps": {
              "expr": {
                "Literal": {
                  "Value": "true"
                }
              }
            },
            "clusteredGapOverlapReverse": {
              "expr": {
                "Literal": {
                  "Value": "true"
                }
              }
            },
            "clusteredGapSize": {
              "expr": {
                "Literal": {
                  "Value": "39D"
                }
              }
            }
          }
        }
      ],
      "labels": [
        {
          "properties": {
            "show": {
              "expr": {
                "Literal": {
                  "Value": "true"
                }
              }
            }
          }
        },
        {
          "properties": {
            "showSeries": {
              "expr": {
                "Literal": {
                  "Value": "false"
                }
              }
            }
          },
          "selector": {
            "metadata": "Calculations.Total Sales"
          }
        }
      ]
    },
    "visualContainerObjects": {
      "title": [
        {
          "properties": {
            "titleWrap": {
              "expr": {
                "Literal": {
                  "Value": "true"
                }
              }
            },
            "fontColor": {
              "solid": {
                "color": {
                  "expr": {
                    "Literal": {
                      "Value": "'#505671'"
                    }
                  }
                }
              }
            },
            "fontSize": {
              "expr": {
                "Literal": {
                  "Value": "11D"
                }
              }
            },
            "bold": {
              "expr": {
                "Literal": {
                  "Value": "true"
                }
              }
            },
            "fontFamily": {
              "expr": {
                "Literal": {
                  "Value": "'Cambria'"
                }
              }
            },
            "text": {
              "expr": {
                "Literal": {
                  "Value": "'Total Sales by State'"
                }
              }
            }
          }
        }
      ],
      "subTitle": [
        {
          "properties": {
            "show": {
              "expr": {
                "Literal": {
                  "Value": "false"
                }
              }
            },
            "fontColor": {
              "solid": {
                "color": {
                  "expr": {
                    "Literal": {
                      "Value": "'#505671'"
                    }
                  }
                }
              }
            },
            "fontSize": {
              "expr": {
                "Literal": {
                  "Value": "8D"
                }
              }
            },
            "text": {
              "expr": {
                "Measure": {
                  "Expression": {
                    "SourceRef": {
                      "Entity": "Calculations"
                    }
                  },
                  "Property": "subTitle_Sales_bySubProd"
                }
              }
            },
            "titleWrap": {
              "expr": {
                "Literal": {
                  "Value": "true"
                }
              }
            }
          }
        }
      ],
      "spacing": [
        {
          "properties": {
            "verticalSpacing": {
              "expr": {
                "Literal": {
                  "Value": "1D"
                }
              }
            }
          }
        }
      ],
      "background": [
        {
          "properties": {
            "show": {
              "expr": {
                "Literal": {
                  "Value": "false"
                }
              }
            },
            "color": {
              "solid": {
                "color": {
                  "expr": {
                    "Literal": {
                      "Value": "'#F9F7F2'"
                    }
                  }
                }
              }
            },
            "transparency": {
              "expr": {
                "Literal": {
                  "Value": "0D"
                }
              }
            }
          }
        }
      ]
    },
    "drillFilterOtherVisuals": true
  },
  "filterConfig": {
    "filters": [
      {
        "name": "84d538d585ac3beec804",
        "field": {
          "Column": {
            "Expression": {
              "SourceRef": {
                "Entity": "Sales Raw Data"
              }
            },
            "Property": "State"
          }
        },
        "type": "TopN",
        "filter": {
          "Version": 2,
          "From": [
            {
              "Name": "subquery",
              "Expression": {
                "Subquery": {
                  "Query": {
                    "Version": 2,
                    "From": [
                      {
                        "Name": "s",
                        "Entity": "Sales Raw Data",
                        "Type": 0
                      },
                      {
                        "Name": "c",
                        "Entity": "Calculations",
                        "Type": 0
                      }
                    ],
                    "Select": [
                      {
                        "Column": {
                          "Expression": {
                            "SourceRef": {
                              "Source": "s"
                            }
                          },
                          "Property": "State"
                        },
                        "Name": "field"
                      }
                    ],
                    "OrderBy": [
                      {
                        "Direction": 2,
                        "Expression": {
                          "Measure": {
                            "Expression": {
                              "SourceRef": {
                                "Source": "c"
                              }
                            },
                            "Property": "Total Sales"
                          }
                        }
                      }
                    ],
                    "Top": 5
                  }
                }
              },
              "Type": 2
            },
            {
              "Name": "s",
              "Entity": "Sales Raw Data",
              "Type": 0
            }
          ],
          "Where": [
            {
              "Condition": {
                "In": {
                  "Expressions": [
                    {
                      "Column": {
                        "Expression": {
                          "SourceRef": {
                            "Source": "s"
                          }
                        },
                        "Property": "State"
                      }
                    }
                  ],
                  "Table": {
                    "SourceRef": {
                      "Source": "subquery"
                    }
                  }
                }
              }
            }
          ]
        }
      }
    ]
  }
}